myhelloworldxyz/__init__.py
myhelloworldxyz/text.py
myhelloworldxyz-0.2.dist-info/METADATA
myhelloworldxyz-0.2.dist-info/WHEEL
myhelloworldxyz-0.2.dist-info/top_level.txt
myhelloworldxyz-0.2.dist-info/RECORD
