Metadata-Version: 2.1
Name: myhelloworldxyz
Version: 0.2
Summary: My Hello World
Home-page: UNKNOWN
Author: ai-linh
Author-email: ailinh.le@gmail.com
License: MIT
Platform: UNKNOWN
Requires-Dist: markdown
